Workbook
Name Orders: #REF!

Sheet Orders
A1: Row ID | B1: Order ID | C1: Order Date | D1: Ship Date | E1: Ship Mode | F1: Customer ID | G1: Customer Name | H1: Segment | I1: Country/Region | J1: City | K1: State/Province | L1: Postal Code | M1: Region | N1: Product ID | O1: Category | P1: Sub-Category | Q1: Product Name | R1: Sales | S1: Quantity | T1: Discount | U1: Profit
A2: 1 | B2: US-2021-103800 | C2: 44199 | D2: 44203 | E2: Standard Class | F2: DP-13000 | G2: Darren Powers | H2: Consumer | I2: United States | J2: Houston | K2: Texas | L2: 77095 | M2: Central | N2: OFF-PA-10000174 | O2: Office Supplies | P2: Paper | Q2: Message Book, Wirebound, Four 5 1/2" X 4" Forms/Pg., 200 Dupl. Sets/Book | R2: 16.448 | S2: 2 | T2: 0.2 | U2: 5.5512
A3: 2 | B3: US-2021-112326 | C3: 44200 | D3: 44204 | E3: Standard Class | F3: PO-19195 | G3: Phillina Ober | H3: Home Office | I3: United States | J3: Naperville | K3: Illinois | L3: 60540 | M3: Central | N3: OFF-BI-10004094 | O3: Office Supplies | P3: Binders | Q3: GBC Standard Plastic Binding Systems Combs | R3: 3.54 | S3: 2 | T3: 0.8 | U3: -5.487
A4: 3 | B4: US-2021-112326 | C4: 44200 | D4: 44204 | E4: Standard Class | F4: PO-19195 | G4: Phillina Ober | H4: Home Office | I4: United States | J4: Naperville | K4: Illinois | L4: 60540 | M4: Central | N4: OFF-LA-10003223 | O4: Office Supplies | P4: Labels | Q4: Avery 508 | R4: 11.784 | S4: 3 | T4: 0.2 | U4: 4.2717
A5: 4 | B5: US-2021-112326 | C5: 44200 | D5: 44204 | E5: Standard Class | F5: PO-19195 | G5: Phillina Ober | H5: Home Office | I5: United States | J5: Naperville | K5: Illinois | L5: 60540 | M5: Central | N5: OFF-ST-10002743 | O5: Office Supplies | P5: Storage | Q5: SAFCO Boltless Steel Shelving | R5: 272.736 | S5: 3 | T5: 0.2 | U5: -64.7748
A6: 5 | B6: US-2021-141817 | C6: 44201 | D6: 44208 | E6: Standard Class | F6: MB-18085 | G6: Mick Brown | H6: Consumer | I6: United States | J6: Philadelphia | K6: Pennsylvania | L6: 19143 | M6: East | N6: OFF-AR-10003478 | O6: Office Supplies | P6: Art | Q6: Avery Hi-Liter EverBold Pen Style Fluorescent Highlighters, 4/Pack | R6: 19.536 | S6: 3 | T6: 0.2 | U6: 4.884
A7: 6 | B7: US-2021-167199 | C7: 44202 | D7: 44206 | E7: Standard Class | F7: ME-17320 | G7: Maria Etezadi | H7: Home Office | I7: United States | J7: Henderson | K7: Kentucky | L7: 42420 | M7: South | N7: FUR-CH-10004063 | O7: Furniture | P7: Chairs | Q7: Global Deluxe High-Back Manager's Chair | R7: 2573.82 | S7: 9 | T7: 0 | U7: 746.4078
A8: 7 | B8: US-2021-167199 | C8: 44202 | D8: 44206 | E8: Standard Class | F8: ME-17320 | G8: Maria Etezadi | H8: Home Office | I8: United States | J8: Henderson | K8: Kentucky | L8: 42420 | M8: South | N8: OFF-AR-10001662 | O8: Office Supplies | P8: Art | Q8: Rogers Handheld Barrel Pencil Sharpener | R8: 5.48 | S8: 2 | T8: 0 | U8: 1.4796
A9: 8 | B9: US-2021-106054 | C9: 44202 | D9: 44203 | E9: First Class | F9: JO-15145 | G9: Jack O'Briant | H9: Corporate | I9: United States | J9: Athens | K9: Georgia | L9: 30605 | M9: South | N9: OFF-AR-10002399 | O9: Office Supplies | P9: Art | Q9: Dixon Prang Watercolor Pencils, 10-Color Set with Brush | R9: 12.78 | S9: 3 | T9: 0 | U9: 5.2398
A10: 9 | B10: US-2021-167199 | C10: 44202 | D10: 44206 | E10: Standard Class | F10: ME-17320 | G10: Maria Etezadi | H10: Home Office | I10: United States | J10: Henderson | K10: Kentucky | L10: 42420 | M10: South | N10: OFF-BI-10004632 | O10: Office Supplies | P10: Binders | Q10: Ibico Hi-Tech Manual Binding System | R10: 609.98 | S10: 2 | T10: 0 | U10: 274.491
A11: 10 | B11: US-2021-167199 | C11: 44202 | D11: 44206 | E11: Standard Class | F11: ME-17320 | G11: Maria Etezadi | H11: Home Office | I11: United States | J11: Henderson | K11: Kentucky | L11: 42420 | M11: South | N11: OFF-FA-10001883 | O11: Office Supplies | P11: Fasteners | Q11: Alliance Super-Size Bands, Assorted Sizes | R11: 31.12 | S11: 4 | T11: 0 | U11: 0.3112
A12: 11 | B12: US-2021-167199 | C12: 44202 | D12: 44206 | E12: Standard Class | F12: ME-17320 | G12: Maria Etezadi | H12: Home Office | I12: United States | J12: Henderson | K12: Kentucky | L12: 42420 | M12: South | N12: OFF-PA-10000955 | O12: Office Supplies | P12: Paper | Q12: Southworth 25% Cotton Granite Paper & Envelopes | R12: 6.54 | S12: 1 | T12: 0 | U12: 3.0084
A13: 12 | B13: US-2021-130813 | C13: 44202 | D13: 44204 | E13: Second Class | F13: LS-17230 | G13: Lycoris Saunders | H13: Consumer | I13: United States | J13: Los Angeles | K13: California | L13: 90049 | M13: West | N13: OFF-PA-10002005 | O13: Office Supplies | P13: Paper | Q13: Xerox 225 | R13: 19.44 | S13: 3 | T13: 0 | U13: 9.3312
... A10195: 10194 | B10195: CA-2024-143500 | C10195: 45656 | D10195: 45660 | E10195: Standard Class | F10195: HO-15230 | G10195: Harry Olson | H10195: Consumer | I10195: Canada | J10195: Charlottetown | K10195: Prince Edward Island | L10195: C0A | M10195: East | N10195: OFF-BI-10004040 | O10195: Office Supplies | P10195: Binders | Q10195: Wilson Jones Impact Binders | R10195: 3.024 | S10195: 3 | T10195: 0.2 | U10195: -0.6048

Sheet Question_1
C2: Average Profit
C3: Category | D3: North | E3: South | F3: Central | G3: West
C4: Furniture | D4: =AVERAGEIFS(Orders!$U$2:$U$10195,Orders!$M$2:$M$10195,Question_1!D$3,Orders!$O$2:$O$10195,Question_1!$C4) -> #DIV/0! | E4: =AVERAGEIFS(Orders!$U$2:$U$10195,Orders!$M$2:$M$10195,Question_1!E$3,Orders!$O$2:$O$10195,Question_1!$C4) -> 20.395199 | F4: =AVERAGEIFS(Orders!$U$2:$U$10195,Orders!$M$2:$M$10195,Question_1!F$3,Orders!$O$2:$O$10195,Question_1!$C4) -> -5.7777458 | G4: =AVERAGEIFS(Orders!$U$2:$U$10195,Orders!$M$2:$M$10195,Question_1!G$3,Orders!$O$2:$O$10195,Question_1!$C4) -> 16.756805
C5: Office Supplies | D5: =AVERAGEIFS(Orders!$U$2:$U$10195,Orders!$M$2:$M$10195,Question_1!D$3,Orders!$O$2:$O$10195,Question_1!$C5) -> #DIV/0! | E5: =AVERAGEIFS(Orders!$U$2:$U$10195,Orders!$M$2:$M$10195,Question_1!E$3,Orders!$O$2:$O$10195,Question_1!$C5) -> 20.086827 | F5: =AVERAGEIFS(Orders!$U$2:$U$10195,Orders!$M$2:$M$10195,Question_1!F$3,Orders!$O$2:$O$10195,Question_1!$C5) -> 6.2727844 | G5: =AVERAGEIFS(Orders!$U$2:$U$10195,Orders!$M$2:$M$10195,Question_1!G$3,Orders!$O$2:$O$10195,Question_1!$C5) -> 28.294207
C6: Technology | D6: =AVERAGEIFS(Orders!$U$2:$U$10195,Orders!$M$2:$M$10195,Question_1!D$3,Orders!$O$2:$O$10195,Question_1!$C6) -> #DIV/0! | E6: =AVERAGEIFS(Orders!$U$2:$U$10195,Orders!$M$2:$M$10195,Question_1!E$3,Orders!$O$2:$O$10195,Question_1!$C6) -> 68.231506 | F6: =AVERAGEIFS(Orders!$U$2:$U$10195,Orders!$M$2:$M$10195,Question_1!F$3,Orders!$O$2:$O$10195,Question_1!$C6) -> 80.231981 | G6: =AVERAGEIFS(Orders!$U$2:$U$10195,Orders!$M$2:$M$10195,Question_1!G$3,Orders!$O$2:$O$10195,Question_1!$C6) -> 73.166946
C8: Total Sales
C9: Category | D9: Consumer | E9: Home Office | F9: Corporate
C10: Furniture | D10: =SUMIFS(Orders!$R$2:$R$10195,Orders!$O$2:$O$10195,$C10,Orders!$H$2:$H$10195,Question_1!D$9) -> 394723.68 | E10: =SUMIFS(Orders!$R$2:$R$10195,Orders!$O$2:$O$10195,$C10,Orders!$H$2:$H$10195,Question_1!E$9) -> 128756.52 | F10: =SUMIFS(Orders!$R$2:$R$10195,Orders!$O$2:$O$10195,$C10,Orders!$H$2:$H$10195,Question_1!F$9) -> 231267.57
C11: Office Supplies | D11: =SUMIFS(Orders!$R$2:$R$10195,Orders!$O$2:$O$10195,$C11,Orders!$H$2:$H$10195,Question_1!D$9) -> 369536.21 | E11: =SUMIFS(Orders!$R$2:$R$10195,Orders!$O$2:$O$10195,$C11,Orders!$H$2:$H$10195,Question_1!E$9) -> 126043.41 | F11: =SUMIFS(Orders!$R$2:$R$10195,Orders!$O$2:$O$10195,$C11,Orders!$H$2:$H$10195,Question_1!F$9) -> 236313.69
C12: Technology | D12: =SUMIFS(Orders!$R$2:$R$10195,Orders!$O$2:$O$10195,$C12,Orders!$H$2:$H$10195,Question_1!D$9) -> 406399.9 | E12: =SUMIFS(Orders!$R$2:$R$10195,Orders!$O$2:$O$10195,$C12,Orders!$H$2:$H$10195,Question_1!E$9) -> 185268.51 | F12: =SUMIFS(Orders!$R$2:$R$10195,Orders!$O$2:$O$10195,$C12,Orders!$H$2:$H$10195,Question_1!F$9) -> 248224.88
I14: Total Profit
H15: Category - Furniture, Region - Central, Segment Consumer and Subcategory = Chair
